<?xml version="1.0" encoding="UTF-8"?><salProspect><jobCd>K000000974</jobCd><jobLrclNm>영업·판매·운전·운송직</jobLrclNm><jobMdclNm>항공기·선박·철도 조종사 및 관제사</jobMdclNm><jobSmclNm>선장 및 항해사</jobSmclNm><sal>조사년도:2023년, 임금 하위(25%) 5100만원, 평균(50%) 6150만원, 상위(25%) 8125만원</sal><jobSatis>63.2</jobSatis><jobProspect>향후 5년간 선장 및 항해사의 고용은 현 상태를 유지 할 전망이다. 해양수산부의 자료에 따르면 선원수첩소지자와 해기면허소지자는 증가하고 있으나, 취업선박은 답보상태를 보이고 있으며, 취업선원은 감소하는 추세에 있다.  반면, 면허 소지자는 다소 증가하여 취업률은 2015년 기준 39.9%로 자격자의 절반 이상이 일자리를 얻지 못하는 것으로 나타났다.
우리나라의 선박은 2010년 6,588척에서 2015년 6,687척으로 다소 증가하였는데, 원양어선과 해외취업선을 제외한 선박에서 증가를 보였다. 외항선과 내항선 등 상선은 증가하여 여객이나 화물 등의 수송이 증가하였음을 볼 수 있다. 선원의 고령화가 심화되어 전체취업선원 중 60세 이상의 비율이 2008년 약 14.5%에서 2015년 약 26.5%로 증가하였다. 이에 따라 향후에는 전체 취업자 수의 변화보다는 고령인력의 은퇴에 따른 신규인력 증원이 나타날 것으로 전망된다.</jobProspect><jobSumProspect><jobProspectNm>증가</jobProspectNm><jobProspectRatio>0</jobProspectRatio><jobProspectInqYr>2023</jobProspectInqYr></jobSumProspect><jobSumProspect><jobProspectNm>다소 증가</jobProspectNm><jobProspectRatio>0</jobProspectRatio><jobProspectInqYr>2023</jobProspectInqYr></jobSumProspect><jobSumProspect><jobProspectNm>유지</jobProspectNm><jobProspectRatio>33</jobProspectRatio><jobProspectInqYr>2023</jobProspectInqYr></jobSumProspect><jobSumProspect><jobProspectNm>다소 감소</jobProspectNm><jobProspectRatio>53</jobProspectRatio><jobProspectInqYr>2023</jobProspectInqYr></jobSumProspect><jobSumProspect><jobProspectNm>감소</jobProspectNm><jobProspectRatio>13</jobProspectRatio><jobProspectInqYr>2023</jobProspectInqYr></jobSumProspect><jobStatus><jobCd>K000000974</jobCd><jobNm>선장 및 항해사</jobNm></jobStatus></salProspect>