<?xml version="1.0" encoding="UTF-8"?><jobSum><jobCd>K000007466</jobCd><jobLrclNm>경영·사무·금융·보험직</jobLrclNm><jobMdclNm>회계·경리 사무원</jobMdclNm><jobSmclNm>경리사무원</jobSmclNm><jobSum>회사 경영에 필요한 재무정보를 제공하기 위하여 현금, 채권, 채무 등의 증감을 기록, 계산, 정리하는 업무를 수행한다.</jobSum><way>경리사무원이 되기 위해서는 고졸 이상의 학력을 요구한다. 경리사무원은 회계사무원과 유사한 업무를 수행하지만 수행하는 업무가 정해진 절차에 따라 매뉴얼이나 전산시스템을 사용하여 청구서, 계산서의 작성, 재무기록의 시스템 입력, 직원의 임금 지급과 경비 증빙서류 정리 등의 업무를 수행하기 때문에 회계사무원보다 요구하는 학력이나 요구하는 전문지식에 차이가 있을 수 있다. 일반적으로 고등학교 상업계열을 졸업하거나 세무회계관련 전산프로그램의 활용능력을 갖추면 취업에 유리하다</way><relMajorList><majorCd>1</majorCd><majorNm>경영학과</majorNm></relMajorList><relMajorList><majorCd>2</majorCd><majorNm>경제학과</majorNm></relMajorList><relMajorList><majorCd>6</majorCd><majorNm>금융·보험학과</majorNm></relMajorList><relMajorList><majorCd>22</majorCd><majorNm>비서학과</majorNm></relMajorList><relMajorList><majorCd>7</majorCd><majorNm>세무·회계학과</majorNm></relMajorList><relMajorList><majorCd>19</majorCd><majorNm>행정학과</majorNm></relMajorList><relCertList><certNm>ERP정보관리사[물류/생산/인사/회계](국가공인 민간)</certNm></relCertList><relCertList><certNm>전산세무회계(국가공인 민간)</certNm></relCertList><relCertList><certNm>전산회계운용사 1,2,3급(국가기술)</certNm></relCertList><sal>조사년도:2023년, 임금 하위(25%) 3000만원, 평균(50%) 3600만원, 상위(25%) 5300만원</sal><jobSatis>64</jobSatis><jobProspect>증가(5%) 현상유지(25%) 감소(68%)</jobProspect><jobStatus>경리사무원</jobStatus><jobAbil>전산(94)/재정 관리(92)/수리력(88)/글쓰기(61)/읽고 이해하기(56)</jobAbil><knowldg>경제와 회계(87)/사무(82)/경영 및 행정(76)/산수와 수학(67)/인사(67)</knowldg><jobEnv>정확성, 정밀성 유지(88)/앉아서 근무(84)/마감시간(81)/이메일 이용하기(80)/전화 대화하기(79)</jobEnv><jobChr>정직성(78)/꼼꼼함(66)/신뢰성(62)/자기통제(49)/인내(46)</jobChr><jobIntrst>관습형(Conventional)(92)/진취형(Enterprising)(31)</jobIntrst><jobVals>신체활동(84)/심신의 안녕(70)/개인지향(55)/지적 추구(51)/자율(49)</jobVals><jobActvImprtncs>행정, 관리 업무(99)/자원 관리(99)/컴퓨터 업무(93)/정보 처리(87)/상사, 동료, 부하직원과 소통(84)</jobActvImprtncs><jobActvLvls>자원 관리(99)/행정, 관리 업무(97)/상사, 동료, 부하직원과 소통(94)/컴퓨터 업무(93)/정보 작성, 기록(92)</jobActvLvls><relJobList><jobCd>K000007487</jobCd><jobNm>회계사무원</jobNm></relJobList></jobSum>