<?xml version="1.0" encoding="UTF-8"?><jobsDo><jobCd>K000000901</jobCd><jobLrclNm>예술·디자인·방송·스포츠직</jobLrclNm><jobMdclNm>연극·영화·방송 전문가</jobMdclNm><jobSmclNm>연극 및 뮤지컬배우</jobSmclNm><jobSum>연극의 등장인물로 출연하여 대본과 감독의 연출에 따라 연기하는 사람을 말한다.</jobSum><execJob>-극중인물을 연기하기 위하여 관련자료를 수집·분석하여 특성, 언어, 성격 등을 연구한다.&#xd;
-대본(시나리오)의 대사를 암기하고 사실적으로 표현하기 위하여 극중 인물의 언어, 동작, 버릇 등을 연습한다.&#xd;
-각 장면과 역할에 어울리는 옷차림, 분장 등을 하고, 상대배우와 연기한다.</execJob><relJobList><jobCd>K000000873</jobCd><jobNm>음향·녹음기사</jobNm></relJobList><relJobList><jobCd>K000000899</jobCd><jobNm>영화배우 및 탤런트</jobNm></relJobList><relJobList><jobCd>K000000951</jobCd><jobNm>모델</jobNm></relJobList><relJobList><jobCd>K000001099</jobCd><jobNm>영상·녹화 및 편집기사</jobNm></relJobList><relJobList><jobCd>K000001126</jobCd><jobNm>개그맨 및 코미디언</jobNm></relJobList><relJobList><jobCd>K000001138</jobCd><jobNm>방송연출가</jobNm></relJobList><relJobList><jobCd>K000001160</jobCd><jobNm>연극영화방송기술감독</jobNm></relJobList><relJobList><jobCd>K000001161</jobCd><jobNm>아나운서</jobNm></relJobList><relJobList><jobCd>K000001207</jobCd><jobNm>리포터</jobNm></relJobList><relJobList><jobCd>K000007458</jobCd><jobNm>영화감독</jobNm></relJobList><relJobList><jobCd>K000007460</jobCd><jobNm>광고영상감독</jobNm></relJobList><relJobList><jobCd>K000007473</jobCd><jobNm>조명기사</jobNm></relJobList><relJobList><jobCd>K000007476</jobCd><jobNm>성우</jobNm></relJobList><relJobList><jobCd>K000007503</jobCd><jobNm>연극연출가</jobNm></relJobList><relJobList><jobCd>K000007543</jobCd><jobNm>촬영기사</jobNm></relJobList></jobsDo>