<?xml version="1.0" encoding="UTF-8"?><jobsDo><jobCd>K000001054</jobCd><jobLrclNm>설치·정비·생산직</jobLrclNm><jobMdclNm>석유·화학물 가공장치 조작원</jobMdclNm><jobSmclNm>화학물가공장치조작원</jobSmclNm><jobSum>산업용 기초 화합물 및 중간 화합물을 제조하기 위하여 파쇄, 가열, 혼합, 증류 또는 여과 화학물을 가공하는 기기를 조작하고, 플라스틱, 고무, 화학섬유 등의 제품 제조를 위한 원료 생산기기를 조작한다.</jobSum><execJob>-고형 화학물 및 기타 재료를 파쇄하고 혼합하는 기계를 조작한다.
-재료를 정화·혼합 또는 합성하고 특수한 성질로 만들거나 화학변화를 일으키는 기계장비를 조작한다.
-화학물 및 관련 재료의 가공을 위해 건조기를 조작한다.
-용액을 여과하는 장치 및 분리시키는 기계를 조작한다.
-천연 액체성 화학물을 화학적·성분별로 분리 또는 정제하는 증류기를 조작한다.
-화학약품 및 기타 첨가제를 석유와 혼합하는 기계를 조작한다.
-생산기록을 작성하고 보관한다.
-장치설비의 이상유무 확인, 간단한 문제 발생시 필요한 조치 활동을 한다.
-생산제품의 1차 품질검사 업무를 수행한다.</execJob><relJobList><jobCd>K000001009</jobCd><jobNm>석유·천연가스제조제어장치조작원</jobNm></relJobList></jobsDo>