<?xml version="1.0" encoding="UTF-8"?><way><jobCd>K000000982</jobCd><jobLrclNm>미용·여행·숙박·음식·경비·청소직</jobLrclNm><jobMdclNm>식당 서비스원</jobMdclNm><jobSmclNm>패스트푸드준비원</jobSmclNm><technKnow>패스트푸드원으로 일하기 위해 특별한 자격이나 학력이 요구되지 않는다. 가게에서 햄버거를 굽거나 용기에 담는 등 단순 반복적인 작업을 수행하므로 취업 후 일정시간 동안 패스트푸드점에서 근무하기 위해 주문을 받는 방법, 패스트푸드 등을 서비스 하는 방법 등에 대한 교육훈련을 받아 활동한다. 무엇보다 용모단정하고 성실한 사람을 요구한다.</technKnow><edubg><edubgMgraduUndr>0</edubgMgraduUndr><edubgHgradu>50</edubgHgradu><edubgCgraduUndr>50</edubgCgraduUndr><edubgUgradu>0</edubgUgradu><edubgGgradu>0</edubgGgradu><edubgDgradu>0</edubgDgradu></edubg><schDpt><cultLangDpt>27</cultLangDpt><socDpt>18</socDpt><eduDpt>0</eduDpt><engnrDpt>45</engnrDpt><natrlDpt>9</natrlDpt><mediDpt>0</mediDpt><artphyDpt>0</artphyDpt></schDpt><kecoList><kecoCd>5321</kecoCd><kecoNm>패스트푸드 준비원</kecoNm></kecoList></way>