<?xml version="1.0" encoding="UTF-8"?><way><jobCd>K000000855</jobCd><jobLrclNm>경영·사무·금융·보험직</jobLrclNm><jobMdclNm>무역·운송·생산·품질 사무원</jobMdclNm><jobSmclNm>물류사무원</jobSmclNm><technKnow>물류사무원이 되기 위해서는 경제학, 경영학, 무역학, 물류학, 산업공학 등 관련 분야의 전문대학 졸업 이상의 학력이 요구된다. 물류관리, 물류시스템, 물류관련 법규, 화물운송, 해운운송, 항공운송, 보관하역 등 물류 전반에 대한 이론적 배경지식이 있어야 하며 물류현장과 시장을 꿰뚫어보는 능력이 필요하다. 특히 이론적 지식뿐 아니라 물류현장의 상황을 이해하고 있어야 하기 때문에 관련 업체나 물류창고, 화물터미널 등 물류현장에서 아르바이트를 해보는 것도 도움이 된다. 물류사무원은 물류운영현장에 대한 이해가 피룡하므로, 기업에서는 관련 인력을 채용한 후 일정 기간 현장 근무를 시키기도 한다. 이 밖에 한국물류협회나 기업부설물류연구소 등에서 물류관리 인력을 위한 전문교육프로그램도 운영하고 있다. 또한, 물류 관련 분야는 국내보다 국외에서 훨씬 발달되어 있어 외국 자료를 접할 일이 많으므로 영어를 비롯한 외국어 실력을 쌓아놓는 것이 필요하다.</technKnow><edubg><edubgMgraduUndr>0</edubgMgraduUndr><edubgHgradu>2</edubgHgradu><edubgCgraduUndr>6</edubgCgraduUndr><edubgUgradu>81</edubgUgradu><edubgGgradu>11</edubgGgradu><edubgDgradu>0</edubgDgradu></edubg><schDpt><cultLangDpt>4</cultLangDpt><socDpt>68</socDpt><eduDpt>0</eduDpt><engnrDpt>24</engnrDpt><natrlDpt>2</natrlDpt><mediDpt>2</mediDpt><artphyDpt>0</artphyDpt></schDpt><relMajorList><majorCd>1</majorCd><majorNm>경영학과</majorNm></relMajorList><relMajorList><majorCd>8</majorCd><majorNm>무역·유통학과</majorNm></relMajorList><relMajorList><majorCd>27</majorCd><majorNm>산업공학과</majorNm></relMajorList><relMajorList><majorCd>6</majorCd><majorNm>지상교통공학과</majorNm></relMajorList><relCertList><certNm>ERP정보관리사[물류/생산/인사/회계](국가공인 민간)</certNm></relCertList><relCertList><certNm>물류관리사(국가전문)</certNm></relCertList><relCertList><certNm>유통관리사(국가전문)</certNm></relCertList><kecoList><kecoCd>0283</kecoCd><kecoNm>자재·구매·물류 사무원</kecoNm></kecoList></way>