<?xml version="1.0" encoding="UTF-8"?><jobsDo><jobCd>K000000855</jobCd><jobLrclNm>경영·사무·금융·보험직</jobLrclNm><jobMdclNm>무역·운송·생산·품질 사무원</jobMdclNm><jobSmclNm>물류사무원</jobSmclNm><jobSum>화물의 유통 촉진과 물류비의 절감을 위해서 물류센터의 운영, 물류관리에 필요한 직무를 수행한다.</jobSum><execJob>-물류의 이동, 보관, 선적 등에 드는 시간 및 노동력을 철저히 파악하여 가장 합리적이고 경제적인 이동계획을 수립하고 이에 대한 책임을 진다.
-하역, 포장, 보관, 수송, 정보, 유통가공 등 물류와 관련한 모든 시스템을 통합 관리한다.
-화물유통, 물류체계, 물류시설과 관련된 지식을 이해하고 이를 활용한다.
-물류시설을 관리하고 상담, 자문 등의 업무를 수행한다.
-기업체의 물류비 등을 계산하고, 연구보고서 등 기타서류를 작성한다.</execJob><relJobList><jobCd>K000000843</jobCd><jobNm>자재·구매사무원</jobNm></relJobList><relJobList><jobCd>K000000918</jobCd><jobNm>무역사무원</jobNm></relJobList><relJobList><jobCd>K000000929</jobCd><jobNm>수상운송사무원</jobNm></relJobList><relJobList><jobCd>K000001001</jobCd><jobNm>생산관리사무원</jobNm></relJobList><relJobList><jobCd>K000001002</jobCd><jobNm>항공운송사무원</jobNm></relJobList><relJobList><jobCd>K000001010</jobCd><jobNm>도로운송사무원</jobNm></relJobList><relJobList><jobCd>K000001022</jobCd><jobNm>품질관리사무원</jobNm></relJobList><relJobList><jobCd>K000001155</jobCd><jobNm>철도·지하철운송사무원</jobNm></relJobList></jobsDo>