<?xml version="1.0" encoding="UTF-8"?><jobSum><jobCd>K000001216</jobCd><jobLrclNm>보건·의료직</jobLrclNm><jobMdclNm>의료기사·치료사·재활사</jobMdclNm><jobSmclNm>예술치료사</jobSmclNm><jobSum>사회적, 심리적, 정서적 문제를 안고 있는 내담자들에게 예술활동을 통해서 갈등문제를 분석, 진단하고 치료한다.</jobSum><way>심리치료를 예술활동을 통해 한다는 점에서 예술과 심리 두 영역에 대한 전문지식이 필수다. 음악이나 미술 등 예술활동과 관련된 공부를 하고, 심리치료에 대한 자격증을 취득하고 진출한다. 치료대상자인 아동이나 청소년, 성인 등에 대한 깊은 이해가 필요하며 심리적으로 문제가 있는 부분을 파악하고 치료계획을 세울 수 있어야 한다. 침착한 태도와 원만한 대인관계능력, 인내심, 포용력, 개방성, 창의성 등을 갖춰야 한다.</way><relMajorList><majorCd>10</majorCd><majorNm>사회복지학과</majorNm></relMajorList><relMajorList><majorCd>14</majorCd><majorNm>심리학과</majorNm></relMajorList><relCertList><certNm>미술치료사자격증, 자격치료사자격증, 음악치료사자격증</certNm></relCertList><sal>조사년도:2023년, 임금 하위(25%) 2575만원, 평균(50%) 3000만원, 상위(25%) 3425만원</sal><jobSatis>75.1</jobSatis><jobProspect>증가(73%) 현상유지(17%) 감소(10%)</jobProspect><jobStatus>예술치료사</jobStatus><jobAbil>사람 파악(94)/가르치기(93)/설득(91)/행동조정(90)/말하기(86)</jobAbil><knowldg>상담(89)/예술(88)/심리(84)/의료(76)/교육 및 훈련(73)</knowldg><jobEnv>앉아서 근무(85)/실내 근무(78)/실수의 심각성(74)/다른 사람과 신체적 접촉(68)/연설, 발표, 회의하기(66)</jobEnv><jobChr>타인에 대한 배려(52)/책임과 진취성(47)/신뢰성(43)/적응성/융통성(41)/혁신(41)</jobChr><jobIntrst>사회형(Social)(96)/예술형(Artistic)(85)</jobIntrst><jobVals>타인에 대한 영향(96)/이타(94)/인정(88)/개인지향(87)/자율(86)</jobVals><jobActvImprtncs>사람들을 배려, 돌봄(99)/사람들에게 영향력 행사(93)/사물, 서비스, 사람의 질 판단(92)/의사 결정, 문제점 해결(90)/사물, 행동, 사건 파악(85)</jobActvImprtncs><jobActvLvls>사람들을 배려, 돌봄(97)/사물, 서비스, 사람의 질 판단(90)/협상, 갈등 해결(86)/사람들에게 영향력 행사(85)/업무상 사람들을 직접 응대(84)</jobActvLvls><relJobList><jobCd>K000000830</jobCd><jobNm>치과위생사</jobNm></relJobList><relJobList><jobCd>K000000864</jobCd><jobNm>재활공학기사</jobNm></relJobList><relJobList><jobCd>K000001017</jobCd><jobNm>방사선사</jobNm></relJobList><relJobList><jobCd>K000001088</jobCd><jobNm>언어치료사</jobNm></relJobList><relJobList><jobCd>K000001186</jobCd><jobNm>청능사</jobNm></relJobList><relJobList><jobCd>K000007501</jobCd><jobNm>물리치료사</jobNm></relJobList><relJobList><jobCd>K000007529</jobCd><jobNm>임상심리사</jobNm></relJobList><relJobList><jobCd>K000007537</jobCd><jobNm>작업치료사</jobNm></relJobList><relJobList><jobCd>K000007544</jobCd><jobNm>임상병리사</jobNm></relJobList><relJobList><jobCd>K000007564</jobCd><jobNm>놀이치료사</jobNm></relJobList><relJobList><jobCd>K000007577</jobCd><jobNm>치과기공사</jobNm></relJobList></jobSum>