<?xml version="1.0" encoding="UTF-8"?><salProspect><jobCd>K000007456</jobCd><jobLrclNm>경영·사무·금융·보험직</jobLrclNm><jobMdclNm>정부·공공 행정 사무원</jobMdclNm><jobSmclNm>병무행정사무원</jobSmclNm><sal>조사년도:2023년, 임금 하위(25%) 3200만원, 평균(50%) 3700만원, 상위(25%) 4250만원</sal><jobSatis>70.8</jobSatis><jobProspect>향후 5년간 병무행정사무원의 고용은 현 상태를 유지할 전망이다. 군대에 가야되는 병역자원 관리하고 병역 의무자에게  징집 및 소집 등 병무행정 업무를 계획하고 시행하는 병무행정공무원은 공무원으로서 현 상태를 유지할 가능성이 높다.</jobProspect><jobSumProspect><jobProspectNm>증가</jobProspectNm><jobProspectRatio>0</jobProspectRatio><jobProspectInqYr>2023</jobProspectInqYr></jobSumProspect><jobSumProspect><jobProspectNm>다소 증가</jobProspectNm><jobProspectRatio>0</jobProspectRatio><jobProspectInqYr>2023</jobProspectInqYr></jobSumProspect><jobSumProspect><jobProspectNm>유지</jobProspectNm><jobProspectRatio>30</jobProspectRatio><jobProspectInqYr>2023</jobProspectInqYr></jobSumProspect><jobSumProspect><jobProspectNm>다소 감소</jobProspectNm><jobProspectRatio>53</jobProspectRatio><jobProspectInqYr>2023</jobProspectInqYr></jobSumProspect><jobSumProspect><jobProspectNm>감소</jobProspectNm><jobProspectRatio>17</jobProspectRatio><jobProspectInqYr>2023</jobProspectInqYr></jobSumProspect><jobStatus><jobCd>K000007456</jobCd><jobNm>병무행정사무원</jobNm></jobStatus></salProspect>