<?xml version="1.0" encoding="UTF-8"?><way><jobCd>K000007579</jobCd><jobLrclNm>미용·여행·숙박·음식·경비·청소직</jobLrclNm><jobMdclNm>주방장 및 조리사</jobMdclNm><jobSmclNm>일식조리사</jobSmclNm><technKnow>일식조리사가 되기 위해서는 조리 및 요리관련 민간교육기관에서 수업을 이수하거나 전문계고등학교의 조리과 및 식품공업과, 전문대학 및 4년제 대학교의 (호텔)조리관련학과, 외식산업관련학과 등에서 이론과 실습을 하는 것이 유리하며 국가자격인 &quot;일식조리사&quot;자격을 취득하는 것이 취업이나 창업에 유리하다. 특히 식품위생법’에 따르면 병원, 학교, 정부투자기관 등 집단급식소, 복어조리업, 120㎡ 이상인 식품접객업자는 조리사 자격증을 소지한 자를 채용하게 되어 있으며, 호텔을 비롯해 대형 음식점에서도 일식조리사 자격 소지자에 한해 채용하는 경우가 많다.
일반적으로 대형음식점이나 특급호텔에서는 조리사 보조원으로 2~3년의 경력을 쌓아야 정식조리사가 되며, 다시 3~4년이 지나야 부주방장이 될 수 있다. 부주방장으로 4~6년의 경력을 쌓고 실력을 인정받으면 주방의 총 책임자인 주방장이 될 수 있다. 이후 근무 경험을 살려 본인이 직접 음식점을 창업하기도 하며 출장조리사로 활동하기도 한다.</technKnow><edubg><edubgMgraduUndr>0</edubgMgraduUndr><edubgHgradu>47</edubgHgradu><edubgCgraduUndr>47</edubgCgraduUndr><edubgUgradu>7</edubgUgradu><edubgGgradu>0</edubgGgradu><edubgDgradu>0</edubgDgradu></edubg><schDpt><cultLangDpt>38</cultLangDpt><socDpt>0</socDpt><eduDpt>0</eduDpt><engnrDpt>44</engnrDpt><natrlDpt>19</natrlDpt><mediDpt>0</mediDpt><artphyDpt>0</artphyDpt></schDpt><relMajorList><majorCd>9</majorCd><majorNm>식품영양학과</majorNm></relMajorList><relMajorList><majorCd>10</majorCd><majorNm>식품조리학과</majorNm></relMajorList><relMajorList><majorCd>3</majorCd><majorNm>호텔·관광경영학과</majorNm></relMajorList><relOrgList><orgSiteUrl>www.ikca.or.kr</orgSiteUrl><orgNm>(사)한국조리사회중앙회</orgNm></relOrgList><relOrgList><orgSiteUrl>www.ekra.or.kr</orgSiteUrl><orgNm>(사)한국음식업중앙회</orgNm></relOrgList><relCertList><certNm>일식조리기능사(국가기술)</certNm></relCertList><relCertList><certNm>일식조리기능사, 산업기사(국가기술)</certNm></relCertList><kecoList><kecoCd>5315</kecoCd><kecoNm>일식 조리사</kecoNm></kecoList></way>