<?xml version="1.0" encoding="UTF-8"?><salProspect><jobCd>K000007581</jobCd><jobLrclNm>연구직 및 공학 기술직</jobLrclNm><jobMdclNm>제도사 및 기타 인쇄·목재 등 공학 기술자 및 시험원</jobMdclNm><jobSmclNm>3D프린팅모델러</jobSmclNm><sal>조사년도:2023년, 임금 하위(25%) 3900만원, 평균(50%) 4500만원, 상위(25%) 6000만원</sal><jobSatis>76.5</jobSatis><jobProspect>향후 3D프린팅모델러는 다소 증가할 것으로 전망된다. 3D 프린터는 본래 기업에서 부품이나 제품을 개발하는 과정에서 빠르고 값싸게 모형을 만들기 위한 용도로 개발되어 사용되었으나, 현재는 3D 프린팅 기술이 발전하여 제조, 건설, 의료, 항공·우주, 로봇, 자동차 등 여러 산업에서 모형 제작을 비롯해 실제 부품이나 제품을 만들어 사용하고 있으며, 건물이나 바이오 인공장기(귀 등)를 만드는 단계까지 응용 분야가 넓어졌다. 이에 따라 예전에 비해 3D 프린터 제조업체나 재료 업체, 콘텐츠 업체도 많아지고 있으며, 관련 산업의 매출도 증가하고 있다. 단종 되거나 구하기 어려운 부품, 인공치아, 인공뼈, 인공관절과 같은 보형물을 제작하는 등 3D 프린터는 다양한 산업 분야에 활용되고 있다. 초창기에는 3D 프린팅에 사용되는 재료가 나일론 등으로 한정되어 있고, 적층 속도 또한 빠르지 않은 단점이 있었다. 하지만 최근에는 컴퓨터의 처리 속도와 재료의 발전으로 3D 프린터의 단점이 개선되면서 관련 시장이 성장하고 있다. 3D 프린터는 제조업 혁신을 이끌 핵심 기술로, 각국에서는 관련 산업을 키우기 위해 노력하고 있고, 우리나라 정부도 3D 프린팅 산업 육성과 전문 인력 양성에 지원과 노력을 하고 있다. 이에 따라 향후 3D프린팅모델러의 일자리도 늘어날 것으로 전망된다.</jobProspect><jobSumProspect><jobProspectNm>증가</jobProspectNm><jobProspectRatio>10</jobProspectRatio><jobProspectInqYr>2023</jobProspectInqYr></jobSumProspect><jobSumProspect><jobProspectNm>다소 증가</jobProspectNm><jobProspectRatio>31</jobProspectRatio><jobProspectInqYr>2023</jobProspectInqYr></jobSumProspect><jobSumProspect><jobProspectNm>유지</jobProspectNm><jobProspectRatio>38</jobProspectRatio><jobProspectInqYr>2023</jobProspectInqYr></jobSumProspect><jobSumProspect><jobProspectNm>다소 감소</jobProspectNm><jobProspectRatio>21</jobProspectRatio><jobProspectInqYr>2023</jobProspectInqYr></jobSumProspect><jobSumProspect><jobProspectNm>감소</jobProspectNm><jobProspectRatio>0</jobProspectRatio><jobProspectInqYr>2023</jobProspectInqYr></jobSumProspect><jobStatus><jobCd>K000007581</jobCd><jobNm>3D프린팅모델러</jobNm></jobStatus></salProspect>