<?xml version="1.0" encoding="UTF-8"?><jobSum><jobCd>K000000965</jobCd><jobLrclNm>설치·정비·생산직</jobLrclNm><jobMdclNm>의복 제조원 및 수선원</jobMdclNm><jobSmclNm>의복·가죽·모피수선원</jobSmclNm><jobSum>불량 의복 및 의류제품(모자, 장갑 등)을 수선표의 표시에 따라 수선·처리한다.</jobSum><way>의복·가죽 및 모피수선원이 되기 위해서는 학력과 상관없이 숙련의복사를 보조하면서 기능을 습득하거나 직업전문학교나 사설학원의 의복 관련 훈련과정을 이수하는 것이 유리하다.</way><relCertList><certNm>양장기능사(국가기술)</certNm></relCertList><sal>조사년도:2023년, 임금 하위(25%) 2400만원, 평균(50%) 2700만원, 상위(25%) 3350만원</sal><jobSatis>60.9</jobSatis><jobProspect>증가(0%) 현상유지(33%) 감소(66%)</jobProspect><jobStatus>의복·가죽·모피수선원</jobStatus><jobAbil>정교한 동작(87)/시력(83)/물적자원 관리(64)/장비의 유지(63)/움직임 통제(62)</jobAbil><knowldg>디자인(81)/고객서비스(72)/영업과 마케팅(71)/상품 제조 및 공정(67)/상담(57)</knowldg><jobEnv>사물, 도구, 조종 장치를 다루기 위해 손사용(97)/실수의 심각성(94)/정확성, 정밀성 유지(94)/외부 고객 대하기(86)/앉아서 근무(80)</jobEnv><jobChr>꼼꼼함(57)/타인에 대한 배려(49)/독립성(48)/혁신(44)/정직성(43)</jobChr><jobIntrst>현실형(Realistic)(92)/예술형(Artistic)(3)</jobIntrst><jobVals>개인지향(86)/자율(83)/심신의 안녕(71)/신체활동(59)/이타(46)</jobVals><jobActvImprtncs>자원 관리(81)/업무상 사람들을 직접 응대(81)/창조적 생각(76)/제품, 사건, 정보의 수치 추정(70)/조직 외부인과 소통(66)</jobActvImprtncs><jobActvLvls>자원 관리(74)/창조적 생각(72)/업무상 사람들을 직접 응대(72)/기계장치 제어(59)/제품, 사건, 정보의 수치 추정(58)</jobActvLvls><relJobList><jobCd>K000001115</jobCd><jobNm>양장·양복제조원</jobNm></relJobList><relJobList><jobCd>K000007457</jobCd><jobNm>한복제조원</jobNm></relJobList></jobSum>