<?xml version="1.0" encoding="UTF-8"?><jobSum><jobCd>K000000988</jobCd><jobLrclNm>설치·정비·생산직</jobLrclNm><jobMdclNm>인쇄기계·사진현상기 조작원</jobMdclNm><jobSmclNm>인쇄기계조작원</jobSmclNm><jobSum>플라스틱 필름이나 시트 등에 다양한 무늬와 색깔을 인쇄 또는 압착하는 장비를 조작·관리한다.</jobSum><way>인쇄기조작원이 되는 데 학력 제한은 없지만 공업계 고등학교나 전문대의 출판디자인과, 인쇄정보공학과, 인쇄미디어학과, 미디어출판과, 전자출판인쇄전공,  등의 학과를 나오면 취업에 유리하다. 관련자격으로 인쇄산업기사, 인쇄기능사, 전자출판기능사 자격이 있다. 이들은 주로 인쇄업체와 신문사에서 근무한다.</way><relCertList><certNm>인쇄기능사, 산업기사, 기사(국가기술)</certNm></relCertList><relCertList><certNm>전자출판기능사(국가기술)</certNm></relCertList><relCertList><certNm>제판산업기사(국가기술)</certNm></relCertList><sal>조사년도:2023년, 임금 하위(25%) 3350만원, 평균(50%) 4200만원, 상위(25%) 4635만원</sal><jobSatis>66.6</jobSatis><jobProspect>증가(0%) 현상유지(4%) 감소(96%)</jobProspect><jobStatus>인쇄기계조작원</jobStatus><jobAbil>장비 선정(89)/작동 점검(88)/고장의 발견.수리(88)/조직체계의 분석 및 평가(83)/조작 및 통제(82)</jobAbil><knowldg>기계(93)/디자인(88)/상품 제조 및 공정(87)/공학과 기술(76)/영업과 마케팅(70)</knowldg><jobEnv>위험한 장비 노출(100)/장비 속도에 보조 맞추기(100)/걷거나 뛰기(99)/소음 노출(99)/균형을 유지하기(99)</jobEnv><jobChr>꼼꼼함(60)/정직성(52)/스트레스 감내성(50)/인내(44)/신뢰성(43)</jobChr><jobIntrst>현실형(Realistic)(97)/탐구형(Investigative)(75)</jobIntrst><jobVals>개인지향(21)/인정(15)/신체활동(15)/자율(14)/지적 추구(11)</jobVals><jobActvImprtncs>기계장비 유지 보수(95)/기계장치 제어(88)/장비, 건축물, 자재 검사(87)/물건 조종, 운반(82)/일반적인 신체활동(77)</jobActvImprtncs><jobActvLvls>기계장비 유지 보수(91)/기계장치 제어(86)/장치, 부품, 장비의 도면 작성, 배치, 지정(80)/차량, 기계, 장비 작동(80)/장비, 건축물, 자재 검사(78)</jobActvLvls><relJobList><jobCd>K000000880</jobCd><jobNm>사진인화·현상기조작원(사진수정 포함)</jobNm></relJobList></jobSum>