<?xml version="1.0" encoding="UTF-8"?><way><jobCd>K000007491</jobCd><jobLrclNm>연구직 및 공학 기술직</jobLrclNm><jobMdclNm>전기·전자공학 기술자 및 시험원</jobMdclNm><jobSmclNm>전기안전기술자</jobSmclNm><technKnow>전기, 전자 계통의 대학, 2~3년제 대학 혹은 특성화 고등학교에서 관련 교과목을 교육받은 후 각 회사에 취업하는 것이 일반적이다. 이러한 교육기관에서는 전력계통, 에너지, 고전압, 제어 및 시스템, 전기 전자재료 분야 등 다양한 전기응용분야와 전자관련 학문을 배운다. 그 밖에도 서울정수기능대학 외 22개 기능대학을 통해서도 교육받을 수 있다. 관련자격증은 『전기공사업법』에 의거 전기공사의 규모별 전기기술자의 시공관리구분을 규정함으로써 전기기술자 이외의 자가 전기공사업무를 수행할 수 없도록 규정하고 있는데 자격증을 취득하면 취업에 유리할 수 있다.</technKnow><edubg><edubgMgraduUndr>0</edubgMgraduUndr><edubgHgradu>0</edubgHgradu><edubgCgraduUndr>0</edubgCgraduUndr><edubgUgradu>87</edubgUgradu><edubgGgradu>10</edubgGgradu><edubgDgradu>3</edubgDgradu></edubg><schDpt><cultLangDpt>0</cultLangDpt><socDpt>3</socDpt><eduDpt>0</eduDpt><engnrDpt>97</engnrDpt><natrlDpt>0</natrlDpt><mediDpt>0</mediDpt><artphyDpt>0</artphyDpt></schDpt><relMajorList><majorCd>16</majorCd><majorNm>(안경)광학과</majorNm></relMajorList><relMajorList><majorCd>17</majorCd><majorNm>에너지공학과</majorNm></relMajorList><relMajorList><majorCd>12</majorCd><majorNm>전기공학과</majorNm></relMajorList><relCertList><certNm>산업계측제어기술사(국가기술)</certNm></relCertList><relCertList><certNm>전기공사산업기사, 기사(국가기술)</certNm></relCertList><relCertList><certNm>전기기능사, 산업기사, 기사, 기능장(국가기술)</certNm></relCertList><kecoList><kecoCd>1531</kecoCd><kecoNm>전기공학 기술자 및 연구원</kecoNm></kecoList></way>