<?xml version="1.0" encoding="UTF-8"?><way><jobCd>K000001206</jobCd><jobLrclNm>경영·사무·금융·보험직</jobLrclNm><jobMdclNm>금융·보험 영업원</jobMdclNm><jobSmclNm>보험모집인</jobSmclNm><technKnow>보험모집인 및 보험설계사가 되기 위해서는 특별히 요구되는 학력, 성별, 나이 등의 제한은 없지만 최근 들어 직종이 전문화되면서 외국계 보험회사는 학력 조건을 제한하기도 한다. 보험중개사(보험개발원), 변액보험판매관리사(금융연수원), 보험설계사(생명보험협회), 등의 자격을 취득하면 업무에 도움이 된다. 보험설계사가 되려면 먼저 생명보험협회와 손해보험협회가 실시하는 보험설계사 자격시험에 합격해야 한다. 생명보험, 손해보험, 제3보험의 구분에 따라 각각 금융위원회가 정하는 연수를 이수한다. 연수중에는 판매화법, 상품지식, 컴퓨터활용능력 등을 배우며 연수후에는 현장 실습을 거쳐 협회에 자격을 등록해야 한다. 또한 보험회사에서는 회사 소속의 보험설계사를 금융감독위원회에 등록하여 관리한다.</technKnow><edubg><edubgMgraduUndr>0</edubgMgraduUndr><edubgHgradu>33</edubgHgradu><edubgCgraduUndr>7</edubgCgraduUndr><edubgUgradu>56</edubgUgradu><edubgGgradu>4</edubgGgradu><edubgDgradu>0</edubgDgradu></edubg><schDpt><cultLangDpt>22</cultLangDpt><socDpt>33</socDpt><eduDpt>3</eduDpt><engnrDpt>22</engnrDpt><natrlDpt>14</natrlDpt><mediDpt>3</mediDpt><artphyDpt>3</artphyDpt></schDpt><relMajorList><majorCd>6</majorCd><majorNm>금융·보험학과</majorNm></relMajorList><relOrgList><orgSiteUrl>&quot;www.klia.or.kr</orgSiteUrl><orgNm>생명보험협회</orgNm></relOrgList><relOrgList><orgSiteUrl>www.knia.or.kr</orgSiteUrl><orgNm>손해보험협회</orgNm></relOrgList><relOrgList><orgSiteUrl>www.kidi.or.kr</orgSiteUrl><orgNm>보험개발원</orgNm></relOrgList><relCertList><certNm>보험계리사(국가전문)</certNm></relCertList><relCertList><certNm>보험중개사(국가전문)</certNm></relCertList><relCertList><certNm>손해사정사(국가전문)</certNm></relCertList><kecoList><kecoCd>0332</kecoCd><kecoNm>보험 모집인 및 투자 권유 대행인</kecoNm></kecoList></way>