<?xml version="1.0" encoding="UTF-8"?><jobsDo><jobCd>K000001056</jobCd><jobLrclNm>농림어업직</jobLrclNm><jobMdclNm>어업 종사자</jobMdclNm><jobSmclNm>양식원</jobSmclNm><jobSum>어류·패류·해조류 양식장에서 시설물을 설치하거나, 먹이를 주고, 양식물을 채취하는 일에 종사한다.</jobSum><execJob>-양식어업자 또는 양식장관리기사의 지휘·감독하에 양식시설 및 구역표시를 하고 종묘를 양식장에 넣는다.
-먹이 수급계획에 따라 먹이를 공급하고 양식장을 관찰하여 양식물의 성장 상태, 각종 병충해, 해상의 변화를 수시로 검사하여 양식장관리기사에게 보고한다.
-양식장의 시설물 및 장비를 청소하고 이동시킨다.
-양식장 바닥의 산성화·노화장지를 위하여 선박을 이용하거나 잠수하여 밑을 간다.
-채취선·채취기구를 사용하여 양식물을 채취한다.
-양식물을 판매하기 위하여 세척·분류하고, 껍질을 벗기거나 삶아 말리며, 포장을 한다.
-도난 방지를 위하여 경비를 한다.
-태풍 등으로 시설물이 파괴되면 보수한다.
-양식이 끝난 시설물을 철거하여 보수·정비한다.</execJob><relJobList><jobCd>K000000926</jobCd><jobNm>어부 및 해녀</jobNm></relJobList></jobsDo>