<?xml version="1.0" encoding="UTF-8"?><way><jobCd>K000000864</jobCd><jobLrclNm>보건·의료직</jobLrclNm><jobMdclNm>의료기사·치료사·재활사</jobMdclNm><jobSmclNm>재활공학기사</jobSmclNm><technKnow>재활공학기사가 되기 위해서는 의료보장구학과 등 관련학과를 전공하여 한국보건의료인국가시험원에서 실시하는 의지보조기기사 시험에 합격해야만 활동할 수 있다.</technKnow><edubg><edubgMgraduUndr>0</edubgMgraduUndr><edubgHgradu>0</edubgHgradu><edubgCgraduUndr>34</edubgCgraduUndr><edubgUgradu>63</edubgUgradu><edubgGgradu>3</edubgGgradu><edubgDgradu>0</edubgDgradu></edubg><schDpt><cultLangDpt>0</cultLangDpt><socDpt>0</socDpt><eduDpt>0</eduDpt><engnrDpt>38</engnrDpt><natrlDpt>0</natrlDpt><mediDpt>62</mediDpt><artphyDpt>0</artphyDpt></schDpt><relMajorList><majorCd>12</majorCd><majorNm>물리치료학과</majorNm></relMajorList><relMajorList><majorCd>14</majorCd><majorNm>의료공학(의료장비)과 </majorNm></relMajorList><relMajorList><majorCd>13</majorCd><majorNm>작업치료학과</majorNm></relMajorList><relMajorList><majorCd>11</majorCd><majorNm>재활학과</majorNm></relMajorList><relCertList><certNm>보조공학사(국가전문)</certNm></relCertList><relCertList><certNm>의공산업기사, 기사(국가기술)</certNm></relCertList><relCertList><certNm>의지보조기기사(국가전문)</certNm></relCertList><kecoList><kecoCd>3067</kecoCd><kecoNm>재활공학 기사</kecoNm></kecoList></way>