<?xml version="1.0" encoding="UTF-8"?><way><jobCd>K000001027</jobCd><jobLrclNm>예술·디자인·방송·스포츠직</jobLrclNm><jobMdclNm>스포츠·레크리에이션 종사자</jobMdclNm><jobSmclNm>스포츠감독 및 코치</jobSmclNm><technKnow>감독 및 코치는 대개 해당 종목의 선수로 활동하던 사람들이다. 선수로 활동하였다고 하더라도 감독이나 코치로 활동하기 위해서는 선수들을 이끌 수 있는 지도력뿐 아니라 이론과 기술적 지식이 필요하기 때문에 대학에서 체육 관련 학문을 전공하는 것이 유리하다. 국민체육진흥공단 체육과학연구원의 지도자연수과정을 이수하고 경기지도자 1, 2급을 취득하는 것이 훨씬 유리한데, 특히 국가대표팀 감독이나 코치가 되기 위해서는 이 자격이 필수적으로 요구된다.  체육교사가 많이 겸임하고 있는 초·중·고등학교의 운동부지도자는 경기지도자 또는 체육 2급 정교사 자격 소지자로 자격을 제한할 것으로 보여 관련 자격을 갖추는 것이 유리하다.</technKnow><edubg><edubgMgraduUndr>0</edubgMgraduUndr><edubgHgradu>3</edubgHgradu><edubgCgraduUndr>13</edubgCgraduUndr><edubgUgradu>81</edubgUgradu><edubgGgradu>0</edubgGgradu><edubgDgradu>3</edubgDgradu></edubg><schDpt><cultLangDpt>3</cultLangDpt><socDpt>0</socDpt><eduDpt>24</eduDpt><engnrDpt>3</engnrDpt><natrlDpt>0</natrlDpt><mediDpt>0</mediDpt><artphyDpt>70</artphyDpt></schDpt><relMajorList><majorCd>11</majorCd><majorNm>경호학과</majorNm></relMajorList><relMajorList><majorCd>10</majorCd><majorNm>예체능교육과</majorNm></relMajorList><relMajorList><majorCd>10</majorCd><majorNm>체육학과</majorNm></relMajorList><relOrgList><orgSiteUrl>www.sports.or.kr</orgSiteUrl><orgNm>대한체육회</orgNm></relOrgList><relOrgList><orgSiteUrl>www.kspo.or.kr</orgSiteUrl><orgNm>국민체육진흥공단</orgNm></relOrgList><relOrgList><orgSiteUrl>www.sports.re.kr</orgSiteUrl><orgNm>국민체육진흥공단 체육과학연구원</orgNm></relOrgList><relCertList><certNm>경기지도사 1, 2급(국가전문)</certNm></relCertList><relCertList><certNm>전문스포츠지도사 1, 2급(국가전문)</certNm></relCertList><kecoList><kecoCd>4201</kecoCd><kecoNm>스포츠 감독 및 코치</kecoNm></kecoList></way>