<?xml version="1.0" encoding="UTF-8"?><salProspect><jobCd>K000001021</jobCd><jobLrclNm>연구직 및 공학 기술직</jobLrclNm><jobMdclNm>건축·토목공학 기술자 및 시험원</jobMdclNm><jobSmclNm>지리정보시스템전문가</jobSmclNm><sal>조사년도:2023년, 임금 하위(25%) 3900만원, 평균(50%) 4900만원, 상위(25%) 6500만원</sal><jobSatis>72.6</jobSatis><jobProspect>향후 5년간 지리정보시스템전문가(GIS전문가)의 고용은 현 상태를 유지하거나 다소 증가할 것으로 전망된다. 측량과 IT기술이 융합된 공간정보의 활용 분야가 매우 다양해지고 있고, 관련 시장도 커지고 있다. 지리공간정보의 활용성이 매우 커져 이제는 건설, 국방, 안전 등 거의 모든 분야에서 활용되고 있다. 가장 대표적인 분야인 내비게이션 서비스에서 활용되는 것 외에도 상하수도 등 지하시설물 정보, 교통·물류 정보, 상권 정보, 부동산 정보, 방범시스템 등의 구축 및 정보제공 분야에서 공공 및 민간 수요가 증가하고 있다. 향후에도 다양한 수요자를 위한 맞춤형 공간정보서비스 산업이 성장할 것으로 예상된다. 또한 지방자치단체에서도 도시정보시스템(UIS) 구축 사업을 적극 추진하고 있다. 정부에서도 위치기반서비스(LBS), 지능형교통체계(ITS) 등 다양한 융·복합 산업의 근간이 되는 국가공간정보를 구축하기 위해 정책적으로 투자를 지속하고 있다. 그 밖에도 스마트폰위치기반서비스, 3차원영상지도 개발, 게임 등 각종 IT콘텐츠 개발에서 활용성이 커지고 있고, 최근에는 드론이나 자율주행자동차의 기술 발전과 함께 지리정보(공간정보)가 더욱 중요해 지고 있다. 향후 지리정보시스템전문가의 활용 영역은 더욱 넓어질 것이고, 일자리 증가도 예상된다.</jobProspect><jobSumProspect><jobProspectNm>증가</jobProspectNm><jobProspectRatio>0</jobProspectRatio><jobProspectInqYr>2023</jobProspectInqYr></jobSumProspect><jobSumProspect><jobProspectNm>다소 증가</jobProspectNm><jobProspectRatio>70</jobProspectRatio><jobProspectInqYr>2023</jobProspectInqYr></jobSumProspect><jobSumProspect><jobProspectNm>유지</jobProspectNm><jobProspectRatio>10</jobProspectRatio><jobProspectInqYr>2023</jobProspectInqYr></jobSumProspect><jobSumProspect><jobProspectNm>다소 감소</jobProspectNm><jobProspectRatio>10</jobProspectRatio><jobProspectInqYr>2023</jobProspectInqYr></jobSumProspect><jobSumProspect><jobProspectNm>감소</jobProspectNm><jobProspectRatio>10</jobProspectRatio><jobProspectInqYr>2023</jobProspectInqYr></jobSumProspect><jobStatus><jobCd>K000001021</jobCd><jobNm>지리정보시스템전문가</jobNm></jobStatus></salProspect>