<?xml version="1.0" encoding="UTF-8"?><salProspect><jobCd>K000001030</jobCd><jobLrclNm>설치·정비·생산직</jobLrclNm><jobMdclNm>운송장비 정비원</jobMdclNm><jobSmclNm>철도기관차·전동차정비원</jobSmclNm><sal>조사년도:2023년, 임금 하위(25%) 4500만원, 평균(50%) 4875만원, 상위(25%) 5500만원</sal><jobSatis>76.1</jobSatis><jobProspect>향후 5년간 철도기관차정비원의 고용은 현 상태를 유지하고, 고속철도 및 전동차정비원의 고용은 다소 증가할 것으로 전망된다. 기후변화로 상징되는 환경 위기와 고유가로 대변되는 자원 위기로 저탄소 친환경 패러다임이 전 세계적인 관심사이자 성장동력으로 대두하면서 나라마다 자원의 효율적·친환경적 이용에 국력을 집중하고 있다. 또한 운송수단의 사고로 인한 인적 물적 자원의 피해를 줄이기 위하여 안전기준을 강화하고 있어 이에 따른 정비원의 수요가 예상된다. 특히, KTX와 같은 고속철도의 증가로 인한 고숙련 정비원의 고용은 증가할 것이며, 대도시를 중심으로 한 지하철 노선확장, 기존 철도의 전철화 사업, 경전철 시스템 도입 등으로 인해 전동차정비원에 대한 추가적인 인력 수요도 있을 것으로 보인다. 그러나 화석연료를 사용하는 철도차량 분야는 노후한 철도를 제3국으로 수출함에 따라 국내 정비의 필요성이 줄어들고 있고, 공기업 및 공공기관의 경영 합리화와 효율성 제고 때문에 노동인력에 대한 추가 수요는 한정적일 것이다. 또한 그동안 2개로 분리되어 운영되던 서울 2대 지하철공사인 서울도시철도공사와 서울메트로가 2016년 상반기까지 합병을 준비하고 있어 이로 인한 중복업무 인원의 감소가 예상된다.</jobProspect><jobSumProspect><jobProspectNm>증가</jobProspectNm><jobProspectRatio>0</jobProspectRatio><jobProspectInqYr>2023</jobProspectInqYr></jobSumProspect><jobSumProspect><jobProspectNm>다소 증가</jobProspectNm><jobProspectRatio>17</jobProspectRatio><jobProspectInqYr>2023</jobProspectInqYr></jobSumProspect><jobSumProspect><jobProspectNm>유지</jobProspectNm><jobProspectRatio>67</jobProspectRatio><jobProspectInqYr>2023</jobProspectInqYr></jobSumProspect><jobSumProspect><jobProspectNm>다소 감소</jobProspectNm><jobProspectRatio>7</jobProspectRatio><jobProspectInqYr>2023</jobProspectInqYr></jobSumProspect><jobSumProspect><jobProspectNm>감소</jobProspectNm><jobProspectRatio>10</jobProspectRatio><jobProspectInqYr>2023</jobProspectInqYr></jobSumProspect><jobStatus><jobCd>K000001030</jobCd><jobNm>철도기관차·전동차정비원</jobNm></jobStatus></salProspect>