<?xml version="1.0" encoding="UTF-8"?><jobSum><jobCd>K000001176</jobCd><jobLrclNm>연구직 및 공학 기술직</jobLrclNm><jobMdclNm>소프트웨어 개발자</jobMdclNm><jobSmclNm>응용소프트웨어개발자</jobSmclNm><jobSum>각종 응용분야의 컴퓨터 소프트웨어를 설계하고 개발한다.</jobSum><way>응용소프트웨어개발자가 되기 위해서는 전문대학 및 대학교의 컴퓨터공학과, 전산(공학)과 등의 관련 학과를 졸업하는 것이 유리하다. 비전공자는 사설교육기관에서 C언어, 자바, 비주얼스튜디오, 델파이, 파워빌더 등 프로그래밍 언어 등을 배우고 진출한다. 최근에 대학에서는 소프트웨어와 관련한 별도의 학과들이 개설되고 있다. 이들 학과에서는 소프트웨어공학, 프로그램언어, 운영체제, 데이터베이스, 자료구조를 비롯해 실제 응용소프트웨어 개발 실습을 한다.</way><relMajorList><majorCd>1</majorCd><majorNm>경영학과</majorNm></relMajorList><relMajorList><majorCd>8</majorCd><majorNm>공학교육과</majorNm></relMajorList><relMajorList><majorCd>1</majorCd><majorNm>교육학과</majorNm></relMajorList><relMajorList><majorCd>14</majorCd><majorNm>물리·과학과</majorNm></relMajorList><relMajorList><majorCd>12</majorCd><majorNm>수학과</majorNm></relMajorList><relMajorList><majorCd>23</majorCd><majorNm>응용소프트웨어공학과</majorNm></relMajorList><relMajorList><majorCd>13</majorCd><majorNm>전자공학과</majorNm></relMajorList><relMajorList><majorCd>25</majorCd><majorNm>정보·통신공학과</majorNm></relMajorList><relMajorList><majorCd>14</majorCd><majorNm>제어계측공학과</majorNm></relMajorList><relMajorList><majorCd>22</majorCd><majorNm>컴퓨터공학과</majorNm></relMajorList><relMajorList><majorCd>13</majorCd><majorNm>통계학과</majorNm></relMajorList><relCertList><certNm>MCSD(외국)</certNm></relCertList><relCertList><certNm>MCSE(외국)</certNm></relCertList><relCertList><certNm>SCJP(외국)</certNm></relCertList><relCertList><certNm>리눅스마스터(국가공인 민간)</certNm></relCertList><relCertList><certNm>전자계산기조직응용기사, 기술사(국가기술)</certNm></relCertList><relCertList><certNm>전자계산조직응용기사, 기술사(국가기술)</certNm></relCertList><relCertList><certNm>정보처리기능사, 산업기사, 기사(국가기술)</certNm></relCertList><sal>조사년도:2023년, 임금 하위(25%) 5000만원, 평균(50%) 6550만원, 상위(25%) 8625만원</sal><jobSatis>72.7</jobSatis><jobProspect>증가(44%) 현상유지(31%) 감소(24%)</jobProspect><jobStatus>응용소프트웨어개발자</jobStatus><jobAbil>기술 분석(100)/전산(100)/기술 설계(99)/조직체계의 분석 및 평가(98)/추리력(96)</jobAbil><knowldg>컴퓨터와 전자공학(94)/공학과 기술(86)/산수와 수학(82)/통신(81)/영어(75)</knowldg><jobEnv>재택근무(93)/자동화 정도(91)/앉아서 근무(88)/이메일 이용하기(83)/실내 근무(76)</jobEnv><jobChr>혁신(72)/협조(72)/분석적 사고(71)/독립성(62)/꼼꼼함(62)</jobChr><jobIntrst>탐구형(Investigative)(79)/진취형(Enterprising)(53)</jobIntrst><jobVals>성취(100)/다양성(98)/이타(93)/신체활동(92)/지적 추구(87)</jobVals><jobActvImprtncs>컴퓨터 업무(99)/창조적 생각(99)/새로운 지식의 습득, 활용(89)/의사 결정, 문제점 해결(86)/정보 수집(85)</jobActvImprtncs><jobActvLvls>창조적 생각(99)/컴퓨터 업무(96)/새로운 지식의 습득, 활용(93)/사람들에게 조언, 상담(91)/조직 외부인과 소통(91)</jobActvLvls><relJobList><jobCd>K000000853</jobCd><jobNm>시스템소프트웨어개발자</jobNm></relJobList><relJobList><jobCd>K000001042</jobCd><jobNm>모바일앱개발자</jobNm></relJobList><relJobList><jobCd>K000001106</jobCd><jobNm>웹개발자</jobNm></relJobList><relJobList><jobCd>K000001153</jobCd><jobNm>IT테스터 및 IT QA전문가</jobNm></relJobList><relJobList><jobCd>K000001172</jobCd><jobNm>웹기획자</jobNm></relJobList><relJobList><jobCd>K000007452</jobCd><jobNm>가상현실전문가</jobNm></relJobList><relJobList><jobCd>K000007580</jobCd><jobNm>게임프로그래머</jobNm></relJobList></jobSum>