<?xml version="1.0" encoding="UTF-8"?><jobsDo><jobCd>K000001057</jobCd><jobLrclNm>설치·정비·생산직</jobLrclNm><jobMdclNm>제화원, 기타 섬유·의복 기계 조작원 및 조립원</jobMdclNm><jobSmclNm>세탁기계조작원</jobSmclNm><jobSum>의류, 섬유직물 및 유사물품을 손으로 세탁 또는 다림질하거나, 세척·세탁하는 기계를 조작한다.</jobSum><execJob>-고객으로부터 의뢰 받은 세탁물을 옷감의 종류에 따라 분류한다.
-세탁물의 정확한 세탁법과 세탁기계 사용법을 숙지한다.
-구분된 세탁물을 물과 세제를 사용하여 물세탁을 한 후 건조기를 사용하여 건조하거나 유기용제를 사용하여 드라이크리닝 한다.
-드라이크리닝 시에는 유기용제의 농도 등을 고려하여 드라이크리닝기를 조작하여 세탁한다.
-연속식 세탁기(터널세탁기)라고 불리는 대형세탁기에 세탁물을 주기적으로 투입한다.
-세탁물의 강도나 때의 농도에 따라 세탁시간을 조정하고 세제량을 조절한다.
-세탁물에 따라 얼룩을 빼거나 특수처리를 한다.
-세탁이 완료 된 후에는 세탁물의 상태를 확인하고 다림질 한 후에 정리한다.
-주기적으로 세탁기계 상태를 점검하고 청소한다.</execJob><relJobList><jobCd>K000001015</jobCd><jobNm>신발제조기계조작원 및 조립원</jobNm></relJobList><relJobList><jobCd>K000001033</jobCd><jobNm>제화원</jobNm></relJobList></jobsDo>